{
  "page_number": 4,
  "source_image": "/Users/nhanvu/Documents/youtuber/comic/comic-video-pipeline/.cache/comic_scraper/series-6587/chapter-34073/page_04.jpg",
  "image_dimensions": {
    "width": 1200,
    "height": 1844
  },
  "is_story_page": true,
  "page_type": "story",
  "panels": [
    {
      "index": 0,
      "bbox": {
        "x": 548,
        "y": 0,
        "w": 603,
        "h": 579
      },
      "description": "A wide view of a high-tech laboratory at the Baxter Building, featuring an empty doorway and a draped object.",
      "characters": [],
      "dominant_emotion": "mysterious"
    },
    {
      "index": 1,
      "bbox": {
        "x": 146,
        "y": 573,
        "w": 940,
        "h": 211
      },
      "description": "A close-up of Ben Grimm (The Thing) wearing a hat and glasses, looking startled by a noise.",
      "characters": [
        "The Thing"
      ],
      "dominant_emotion": "surprised"
    },
    {
      "index": 2,
      "bbox": {
        "x": 135,
        "y": 804,
        "w": 930,
        "h": 541
      },
      "description": "The Thing enters the frame, investigating a draped figure or object in the laboratory.",
      "characters": [
        "The Thing"
      ],
      "dominant_emotion": "curious"
    },
    {
      "index": 3,
      "bbox": {
        "x": 589,
        "y": 801,
        "w": 487,
        "h": 541
      },
      "description": "A split panel showing a close-up of The Thing's face on the left and a shadowy, organic shape under a drape on the right.",
      "characters": [
        "The Thing"
      ],
      "dominant_emotion": "intense"
    },
    {
      "index": 4,
      "bbox": {
        "x": 46,
        "y": 1356,
        "w": 619,
        "h": 405
      },
      "description": "A close-up of The Thing's face as he realizes something startling.",
      "characters": [
        "The Thing"
      ],
      "dominant_emotion": "shocked"
    },
    {
      "index": 5,
      "bbox": {
        "x": 670,
        "y": 1360,
        "w": 479,
        "h": 403
      },
      "description": "A close-up of a dark, amorphous shadow moving beneath a white sheet.",
      "characters": [],
      "dominant_emotion": "unsettling"
    }
  ],
  "text_blocks": [
    {
      "panel_index": -1,
      "text": "THE BAXTER BUILDING.",
      "type": "caption",
      "speaker": null
    },
    {
      "panel_index": 0,
      "text": "...and the Thing.",
      "type": "caption",
      "speaker": null
    },
    {
      "panel_index": 0,
      "text": "REED? YA IN HERE? WE WAS SUPPOSED TO MEET OUT AT THE CRASH SITE.",
      "type": "speech",
      "speaker": "The Thing"
    },
    {
      "panel_index": 0,
      "text": "WORLD'S SMARTEST GUY AND YET HE'D FORGET ABOUT A DAY LIKE TODAY...",
      "type": "caption",
      "speaker": null
    },
    {
      "panel_index": 1,
      "text": "WHAK",
      "type": "sfx",
      "speaker": null
    },
    {
      "panel_index": 1,
      "text": "WHAT--?",
      "type": "speech",
      "speaker": "The Thing"
    },
    {
      "panel_index": 2,
      "text": "WHAK",
      "type": "sfx",
      "speaker": null
    },
    {
      "panel_index": 2,
      "text": "IS THAT THING...",
      "type": "speech",
      "speaker": "The Thing"
    },
    {
      "panel_index": 4,
      "text": "...ALIVE?",
      "type": "speech",
      "speaker": "The Thing"
    },
    {
      "panel_index": 5,
      "text": "BASED PURELY ON OUR KNOWN DEFINITION OF LIFE AS THE CAPACITY FOR METABOLISM, GROWTH, REPRODUCTION AND FUNCTIONAL ACTIVITY...",
      "type": "caption",
      "speaker": null
    }
  ],
  "page_summary": "The Thing arrives at the Baxter Building looking for Reed Richards, only to find the lab empty and hear a strange noise. He discovers a draped, moving object in the lab, leading him to realize with shock that something might be alive beneath the sheet.",
  "issue_label": "#1",
  "vlm_model": "google/gemma-4-26b-a4b-it:free",
  "content_hash": "cd1c25694444fa2a",
  "preprocessing_method": "yolo+vlm",
  "skip_reason": ""
}